LICENSE
akerun_sum/cli.py
changelog.rst
akerun_sum-1.2.2.dist-info/entry_points.txt
akerun_sum-1.2.2.dist-info/LICENSE
akerun_sum-1.2.2.dist-info/WHEEL
akerun_sum-1.2.2.dist-info/METADATA
akerun_sum-1.2.2.dist-info/RECORD
