Metadata-Version: 2.1
Name: akerun-sum
Version: 1.2.2
Summary: Enter and leave data totalization program for Akerun
Home-page: https://github.com/osstech-jp/akerun-sum
License: GPL-3.0-or-later
Keywords: akerun,akerun-sum
Author: KAWAI Shun
Author-email: shun@osstech.co.jp
Maintainer: KAWAI Shun
Maintainer-email: shun@osstech.co.jp
Requires-Python: >=3.5
Classifier: Environment :: Console
Classifier: License :: OSI Approved :: GNU General Public License (GPL)
Classifier: License :: OSI Approved :: GNU General Public License v3 or later (GPLv3+)
Classifier: Natural Language :: Japanese
Classifier: Operating System :: Microsoft :: Windows :: Windows 7
Classifier: Operating System :: POSIX :: Linux
Classifier: Programming Language :: Python :: 3
Classifier: Programming Language :: Python :: 3.5
Classifier: Programming Language :: Python :: 3.6
Classifier: Programming Language :: Python :: 3.7
Classifier: Programming Language :: Python :: 3.8
Requires-Dist: click (>=7.1)
Project-URL: Repository, https://github.com/osstech-jp/akerun-sum
